operacionesprimos/primo.py
operacionesprimos-1.0.dist-info/LICENSE.txt
operacionesprimos-1.0.dist-info/METADATA
operacionesprimos-1.0.dist-info/WHEEL
operacionesprimos-1.0.dist-info/top_level.txt
operacionesprimos-1.0.dist-info/RECORD
