Metadata-Version: 2.1
Name: operacionesprimos
Version: 1.0
Summary: A tool to perfotm mathematical operations.
Home-page: UNKNOWN
Author: Adrian Valverde
Author-email: adrianvalverdegarrido@hotmail.com
License: GNU GPLv3
Keywords: pyoperaciones mathematical operations
Platform: UNKNOWN
Classifier: Development Status :: 4 - Beta
Classifier: Intended Audience :: Developers
Classifier: Topic :: Utilities
Classifier: License :: OSI Approved :: GNU General Public License v3 (GPLv3)
Classifier: Programming Language :: Python :: 3
Classifier: Operating System :: OS Independent
License-File: LICENSE.txt
